cve_vulnerability_scanner/__init__.py
cve_vulnerability_scanner/main.py
cve_vulnerability_scanner-1.0.1.dist-info/licenses/LICENSE
cve_vulnerability_scanner-1.0.1.dist-info/METADATA
cve_vulnerability_scanner-1.0.1.dist-info/WHEEL
cve_vulnerability_scanner-1.0.1.dist-info/entry_points.txt
cve_vulnerability_scanner-1.0.1.dist-info/top_level.txt
cve_vulnerability_scanner-1.0.1.dist-info/RECORD
