Metadata-Version: 2.4
Name: cve-vulnerability-scanner
Version: 1.0.1
Summary: A Python tool that scans software dependencies for known vulnerabilities using NIST's National Vulnerability Database (NVD)
Home-page: https://github.com/changyy/py-cve-vulnerability-scanner
Author: changyy
Author-email: changyy.csie@gmail.com
Project-URL: Bug Tracker, https://github.com/changyy/py-cve-vulnerability-scanner/issues
Project-URL: Documentation, https://github.com/changyy/py-cve-vulnerability-scanner#readme
Project-URL: Source Code, https://github.com/changyy/py-cve-vulnerability-scanner
Keywords: cve security vulnerability scanner nvd nist
Classifier: Development Status :: 3 - Alpha
Classifier: Intended Audience :: Developers
Classifier: Intended Audience :: System Administrators
Classifier: Topic :: Security
Classifier: Topic :: Software Development :: Libraries :: Python Modules
Classifier: Topic :: System :: Software Distribution
Classifier: License :: OSI Approved :: MIT License
Classifier: Operating System :: OS Independent
Classifier: Programming Language :: Python :: 3
Classifier: Programming Language :: Python :: 3.8
Classifier: Programming Language :: Python :: 3.9
Classifier: Programming Language :: Python :: 3.10
Requires-Python: >=3.8
License-File: LICENSE
Requires-Dist: requests>=2.25.0
Provides-Extra: dev
Requires-Dist: pytest>=6.0; extra == "dev"
Requires-Dist: pytest-cov>=2.0; extra == "dev"
Requires-Dist: black>=22.0; extra == "dev"
Requires-Dist: flake8>=3.9; extra == "dev"
Requires-Dist: mypy>=0.900; extra == "dev"
Dynamic: author
Dynamic: author-email
Dynamic: classifier
Dynamic: description
Dynamic: description-content-type
Dynamic: home-page
Dynamic: keywords
Dynamic: license-file
Dynamic: project-url
Dynamic: provides-extra
Dynamic: requires-dist
Dynamic: requires-python
Dynamic: summary
